indiapincodefinder/__init__.py
indiapincodefinder/main.py
indiapincodefinder/utils.py
indiapincodefinder/data/pincode.json
indiapincodefinder-1.2.0.dist-info/METADATA
indiapincodefinder-1.2.0.dist-info/WHEEL
indiapincodefinder-1.2.0.dist-info/top_level.txt
indiapincodefinder-1.2.0.dist-info/RECORD
